meissner/__init__.py
meissner/logger.py
meissner/meissner.py
meissner/mutator.py
meissner/pooler.py
meissner/dictionary/ctf.txt
meissner/dictionary/small.txt
meissner/engines/__init__.py
meissner/engines/seleniumengine.py
meissner/filters/__init__.py
meissner/filters/urlencode.py
meissner/harnesses/__init__.py
meissner/harnesses/commandharness.py
meissner/harnesses/urlharness.py
meissner-1.0.2.data/scripts/meissner
meissner-1.0.2.dist-info/LICENSE
meissner-1.0.2.dist-info/METADATA
meissner-1.0.2.dist-info/WHEEL
meissner-1.0.2.dist-info/top_level.txt
meissner-1.0.2.dist-info/RECORD
