Metadata-Version: 2.1
Name: meissner
Version: 1.0.2
Summary: a dictionary-based XSS mutation fuzzer
Home-page: https://github.com/Arinerron/meissner
Author: Aaron Esau
Author-email: python@aaronesau.com
License: UNKNOWN
Keywords: ctf xss hacking mutation fuzzer fuzzing fuzz dictionary attack attacking injection scripting
Platform: UNKNOWN
Requires-Python: >=3.6
Requires-Dist: smartbytes
Requires-Dist: selenium
Requires-Dist: requests
